wpadmin/__init__.py
wpadmin/utils.py
wpadmin/locale/bg/LC_MESSAGES/django.mo
wpadmin/locale/bg/LC_MESSAGES/django.po
wpadmin/locale/bg_BG/LC_MESSAGES/django.mo
wpadmin/locale/bg_BG/LC_MESSAGES/django.po
wpadmin/locale/de/LC_MESSAGES/django.mo
wpadmin/locale/de/LC_MESSAGES/django.po
wpadmin/locale/fr/LC_MESSAGES/django.mo
wpadmin/locale/fr/LC_MESSAGES/django.po
wpadmin/locale/id/LC_MESSAGES/django.mo
wpadmin/locale/id/LC_MESSAGES/django.po
wpadmin/locale/it/LC_MESSAGES/django.mo
wpadmin/locale/it/LC_MESSAGES/django.po
wpadmin/locale/nl_NL/LC_MESSAGES/django.mo
wpadmin/locale/nl_NL/LC_MESSAGES/django.po
wpadmin/locale/pl/LC_MESSAGES/django.mo
wpadmin/locale/pl/LC_MESSAGES/django.po
wpadmin/locale/pt_BR/LC_MESSAGES/django.mo
wpadmin/locale/pt_BR/LC_MESSAGES/django.po
wpadmin/locale/ru/LC_MESSAGES/django.mo
wpadmin/locale/ru/LC_MESSAGES/django.po
wpadmin/menu/__init__.py
wpadmin/menu/items.py
wpadmin/menu/menus.py
wpadmin/menu/utils.py
wpadmin/static/wpadmin/css/LICENSE-FONT-AWESOME.txt
wpadmin/static/wpadmin/css/font-awesome.min.css
wpadmin/static/wpadmin/css/wpadmin.css
wpadmin/static/wpadmin/css/themes/blue.css
wpadmin/static/wpadmin/css/themes/coffee.css
wpadmin/static/wpadmin/css/themes/default.css
wpadmin/static/wpadmin/css/themes/ectoplasm.css
wpadmin/static/wpadmin/css/themes/light.css
wpadmin/static/wpadmin/css/themes/midnight.css
wpadmin/static/wpadmin/css/themes/milo-light.css
wpadmin/static/wpadmin/css/themes/milo.css
wpadmin/static/wpadmin/css/themes/ocean.css
wpadmin/static/wpadmin/css/themes/sunrise.css
wpadmin/static/wpadmin/fonts/FontAwesome.otf
wpadmin/static/wpadmin/fonts/LICENSE-FONT-AWESOME.txt
wpadmin/static/wpadmin/fonts/fontawesome-webfont.eot
wpadmin/static/wpadmin/fonts/fontawesome-webfont.svg
wpadmin/static/wpadmin/fonts/fontawesome-webfont.ttf
wpadmin/static/wpadmin/fonts/fontawesome-webfont.woff
wpadmin/static/wpadmin/fonts/fontawesome-webfont.woff2
wpadmin/static/wpadmin/js/content.js
wpadmin/static/wpadmin/js/menus.js
django_wpadmin-1.8.0.dist-info/LICENSE.txt
django_wpadmin-1.8.0.dist-info/METADATA
django_wpadmin-1.8.0.dist-info/WHEEL
django_wpadmin-1.8.0.dist-info/top_level.txt
django_wpadmin-1.8.0.dist-info/RECORD
