Metadata-Version: 2.1
Name: django-wpadmin
Version: 1.8.0
Summary: WordPress look and feel for Django administration panel.
Home-page: https://github.com/barszczmm/django-wpadmin
Author: Maciej Marczewski (barszcz)
Author-email: maciej@marczewski.net.pl
License: MIT License
Keywords: wordpress django admin
Platform: UNKNOWN
Classifier: Development Status :: 4 - Beta
Classifier: Environment :: Web Environment
Classifier: Framework :: Django
Classifier: Intended Audience :: Developers
Classifier: Intended Audience :: System Administrators
Classifier: License :: OSI Approved :: MIT License
Classifier: Operating System :: OS Independent
Classifier: Programming Language :: Python
Classifier: Topic :: Software Development
Classifier: Topic :: Software Development :: User Interfaces
Classifier: Topic :: Software Development :: Libraries :: Python Modules
